zuper_loghandle.cpython-310-aarch64-linux-gnu.so
zuper_loghandle.pyi
zuper_loghandle_z7-7.3.2201261049.dist-info/METADATA
zuper_loghandle_z7-7.3.2201261049.dist-info/WHEEL
zuper_loghandle_z7-7.3.2201261049.dist-info/top_level.txt
zuper_loghandle_z7-7.3.2201261049.dist-info/zip-safe
zuper_loghandle_z7-7.3.2201261049.dist-info/RECORD
