Metadata-Version: 2.1
Name: zuper-loghandle-z7
Version: 7.3.2201261049
Summary: UNKNOWN
Home-page: https://github.com/zupermind/zuper-loghandle
Author: Andrea Censi
Author-email: info@zupermind.com
License: UNKNOWN
Platform: UNKNOWN
Requires-Dist: aiofiles
Requires-Dist: termcolor
Requires-Dist: zuper-commons-z7
Requires-Dist: zuper-utils-asyncio-z7
Requires-Dist: zuper-zapp-interfaces-z7
Provides-Extra: test
